{
  "testId" : "1-verify-that-post-page-displays-correctly-on-mobile-device",
  "name" : "Verify that post page displays correctly  on mobile device",
  "report" : {
    "nodes" : [ {
      "name" : "Verify that post page displays correctly ",
      "status" : "info",
      "nodes" : [ {
        "name" : "Type \"admin\" to email on Login page",
        "status" : "info",
        "nodes" : [ {
          "name" : "css: input#user_login",
          "type" : "text"
        } ],
        "time" : 1558599765996,
        "type" : "node"
      }, {
        "name" : "Type \"123456789\" to password on Login page",
        "status" : "info",
        "nodes" : [ {
          "name" : "css: input#user_pass",
          "type" : "text"
        } ],
        "time" : 1558599766052,
        "type" : "node"
      }, {
        "name" : "Click submitButton on Login page",
        "status" : "info",
        "nodes" : [ {
          "name" : "css: input#wp-submit",
          "type" : "text"
        } ],
        "time" : 1558599766096,
        "type" : "node"
      }, {
        "name" : "Click navigation on Dashboard Page",
        "status" : "info",
        "nodes" : [ {
          "name" : "xpath: //div[@id='wpwrap']//div[@id='wpcontent']//li[@id='wp-admin-bar-menu-toggle']//span[@class='ab-icon']",
          "type" : "text"
        } ],
        "time" : 1558599766972,
        "type" : "node"
      }, {
        "name" : "Click linkPost on Dashboard Page",
        "status" : "info",
        "nodes" : [ {
          "name" : "xpath: //div[@class='wp-menu-name' and text()= 'Posts']",
          "type" : "text"
        } ],
        "time" : 1558599767023,
        "type" : "node"
      }, {
        "name" : "Click dismissButton on Post page",
        "status" : "info",
        "nodes" : [ {
          "name" : "css: .nux-dot-tip__disable",
          "type" : "text"
        } ],
        "time" : 1558599769470,
        "type" : "node"
      }, {
        "name" : "Check layout: specs/post/postPage.gspec included tags: mobile",
        "status" : "info",
        "time" : 1558599771260,
        "includedTags" : [ "mobile" ],
        "sections" : [ {
          "name" : "Skeleton",
          "place" : {
            "filePath" : "specs/post/postPage.gspec",
            "lineNumber" : 36
          },
          "objects" : [ {
            "name" : "toolbar",
            "specs" : [ {
              "status" : "info",
              "place" : {
                "filePath" : "specs/post/postPage.gspec",
                "lineNumber" : 70
              },
              "name" : "above editor_body.content_label",
              "meta" : [ {
                "from" : {
                  "object" : "toolbar",
                  "edge" : "bottom"
                },
                "to" : {
                  "object" : "editor_body.content_label",
                  "edge" : "top"
                },
                "expectedDistance" : ">= 0px",
                "realDistance" : "93px"
              } ],
              "highlight" : [ "toolbar", "editor_body.content_label" ]
            }, {
              "status" : "info",
              "place" : {
                "filePath" : "specs/post/postPage.gspec",
                "lineNumber" : 71
              },
              "name" : "inside screen 50px top, 2px left",
              "meta" : [ {
                "from" : {
                  "object" : "toolbar",
                  "edge" : "top"
                },
                "to" : {
                  "object" : "screen",
                  "edge" : "top"
                },
                "expectedDistance" : "50px",
                "realDistance" : "50px"
              }, {
                "from" : {
                  "object" : "toolbar",
                  "edge" : "left"
                },
                "to" : {
                  "object" : "screen",
                  "edge" : "left"
                },
                "expectedDistance" : "2px",
                "realDistance" : "2px"
              } ],
              "highlight" : [ "toolbar", "screen" ]
            }, {
              "status" : "info",
              "place" : {
                "filePath" : "specs/post/postPage.gspec",
                "lineNumber" : 72
              },
              "name" : "left-of header__settings",
              "meta" : [ {
                "from" : {
                  "object" : "toolbar",
                  "edge" : "right"
                },
                "to" : {
                  "object" : "header__settings",
                  "edge" : "left"
                },
                "expectedDistance" : ">= 0px",
                "realDistance" : "256px"
              } ],
              "highlight" : [ "toolbar", "header__settings" ]
            }, {
              "status" : "info",
              "place" : {
                "filePath" : "specs/post/postPage.gspec",
                "lineNumber" : 73
              },
              "name" : "width 36px",
              "meta" : [ {
                "from" : {
                  "object" : "toolbar",
                  "edge" : "left"
                },
                "to" : {
                  "object" : "toolbar",
                  "edge" : "right"
                },
                "expectedDistance" : "36px",
                "realDistance" : "36px"
              } ],
              "highlight" : [ "toolbar" ]
            }, {
              "status" : "info",
              "place" : {
                "filePath" : "specs/post/postPage.gspec",
                "lineNumber" : 83
              },
              "name" : "height 47px",
              "meta" : [ {
                "from" : {
                  "object" : "toolbar",
                  "edge" : "top"
                },
                "to" : {
                  "object" : "toolbar",
                  "edge" : "bottom"
                },
                "expectedDistance" : "47px",
                "realDistance" : "47px"
              } ],
              "highlight" : [ "toolbar" ]
            } ]
          }, {
            "name" : "editor_body.title_textfield",
            "specs" : [ {
              "status" : "info",
              "place" : {
                "filePath" : "specs/post/postPage.gspec",
                "lineNumber" : 76
              },
              "name" : "height 84px",
              "meta" : [ {
                "from" : {
                  "object" : "editor_body.title_textfield",
                  "edge" : "top"
                },
                "to" : {
                  "object" : "editor_body.title_textfield",
                  "edge" : "bottom"
                },
                "expectedDistance" : "84px",
                "realDistance" : "84px"
              } ],
              "highlight" : [ "editor_body.title_textfield" ]
            }, {
              "status" : "info",
              "place" : {
                "filePath" : "specs/post/postPage.gspec",
                "lineNumber" : 77
              },
              "name" : "inside editor_body 0px left right, 45px top",
              "meta" : [ {
                "from" : {
                  "object" : "editor_body.title_textfield",
                  "edge" : "left"
                },
                "to" : {
                  "object" : "editor_body",
                  "edge" : "left"
                },
                "expectedDistance" : "0px",
                "realDistance" : "0px"
              }, {
                "from" : {
                  "object" : "editor_body.title_textfield",
                  "edge" : "right"
                },
                "to" : {
                  "object" : "editor_body",
                  "edge" : "right"
                },
                "expectedDistance" : "0px",
                "realDistance" : "0px"
              }, {
                "from" : {
                  "object" : "editor_body.title_textfield",
                  "edge" : "top"
                },
                "to" : {
                  "object" : "editor_body",
                  "edge" : "top"
                },
                "expectedDistance" : "45px",
                "realDistance" : "45px"
              } ],
              "highlight" : [ "editor_body.title_textfield", "editor_body" ]
            }, {
              "status" : "info",
              "place" : {
                "filePath" : "specs/post/postPage.gspec",
                "lineNumber" : 89
              },
              "name" : "centered horizontally inside editor_body 1px",
              "highlight" : [ "editor_body.title_textfield", "editor_body" ]
            } ]
          }, {
            "name" : "header__settings",
            "specs" : [ {
              "status" : "info",
              "place" : {
                "filePath" : "specs/post/postPage.gspec",
                "lineNumber" : 80
              },
              "name" : "inside screen 50px top, 3px right",
              "meta" : [ {
                "from" : {
                  "object" : "header__settings",
                  "edge" : "top"
                },
                "to" : {
                  "object" : "screen",
                  "edge" : "top"
                },
                "expectedDistance" : "50px",
                "realDistance" : "50px"
              }, {
                "from" : {
                  "object" : "header__settings",
                  "edge" : "right"
                },
                "to" : {
                  "object" : "screen",
                  "edge" : "right"
                },
                "expectedDistance" : "3px",
                "realDistance" : "3px"
              } ],
              "highlight" : [ "header__settings", "screen" ]
            }, {
              "status" : "info",
              "place" : {
                "filePath" : "specs/post/postPage.gspec",
                "lineNumber" : 83
              },
              "name" : "height 47px",
              "meta" : [ {
                "from" : {
                  "object" : "header__settings",
                  "edge" : "top"
                },
                "to" : {
                  "object" : "header__settings",
                  "edge" : "bottom"
                },
                "expectedDistance" : "47px",
                "realDistance" : "47px"
              } ],
              "highlight" : [ "header__settings" ]
            } ]
          }, {
            "name" : "editor_body.content_label",
            "specs" : [ {
              "status" : "info",
              "place" : {
                "filePath" : "specs/post/postPage.gspec",
                "lineNumber" : 86
              },
              "name" : "inside screen 15px left, >= 2px right",
              "meta" : [ {
                "from" : {
                  "object" : "editor_body.content_label",
                  "edge" : "left"
                },
                "to" : {
                  "object" : "screen",
                  "edge" : "left"
                },
                "expectedDistance" : "15px",
                "realDistance" : "15px"
              }, {
                "from" : {
                  "object" : "editor_body.content_label",
                  "edge" : "right"
                },
                "to" : {
                  "object" : "screen",
                  "edge" : "right"
                },
                "expectedDistance" : ">= 2px",
                "realDistance" : "464px"
              } ],
              "highlight" : [ "editor_body.content_label", "screen" ]
            } ]
          }, {
            "name" : "editor_body.content_textfield",
            "specs" : [ {
              "status" : "info",
              "place" : {
                "filePath" : "specs/post/postPage.gspec",
                "lineNumber" : 89
              },
              "name" : "centered horizontally inside editor_body 1px",
              "highlight" : [ "editor_body.content_textfield", "editor_body" ]
            }, {
              "status" : "info",
              "place" : {
                "filePath" : "specs/post/postPage.gspec",
                "lineNumber" : 92
              },
              "name" : "inside editor_body 0px left right bottom",
              "meta" : [ {
                "from" : {
                  "object" : "editor_body.content_textfield",
                  "edge" : "left"
                },
                "to" : {
                  "object" : "editor_body",
                  "edge" : "left"
                },
                "expectedDistance" : "0px",
                "realDistance" : "0px"
              }, {
                "from" : {
                  "object" : "editor_body.content_textfield",
                  "edge" : "right"
                },
                "to" : {
                  "object" : "editor_body",
                  "edge" : "right"
                },
                "expectedDistance" : "0px",
                "realDistance" : "0px"
              }, {
                "from" : {
                  "object" : "editor_body.content_textfield",
                  "edge" : "bottom"
                },
                "to" : {
                  "object" : "editor_body",
                  "edge" : "bottom"
                },
                "expectedDistance" : "0px",
                "realDistance" : "0px"
              } ],
              "highlight" : [ "editor_body.content_textfield", "editor_body" ]
            } ]
          }, {
            "name" : "header__settings.show_more_tool_button",
            "specs" : [ {
              "status" : "info",
              "place" : {
                "filePath" : "specs/post/postPage.gspec",
                "lineNumber" : 95
              },
              "name" : "height 36px",
              "meta" : [ {
                "from" : {
                  "object" : "header__settings.show_more_tool_button",
                  "edge" : "top"
                },
                "to" : {
                  "object" : "header__settings.show_more_tool_button",
                  "edge" : "bottom"
                },
                "expectedDistance" : "36px",
                "realDistance" : "36px"
              } ],
              "highlight" : [ "header__settings.show_more_tool_button" ]
            }, {
              "status" : "info",
              "place" : {
                "filePath" : "specs/post/postPage.gspec",
                "lineNumber" : 96
              },
              "name" : "inside screen 2px right, 55px top",
              "meta" : [ {
                "from" : {
                  "object" : "header__settings.show_more_tool_button",
                  "edge" : "right"
                },
                "to" : {
                  "object" : "screen",
                  "edge" : "right"
                },
                "expectedDistance" : "2px",
                "realDistance" : "2px"
              }, {
                "from" : {
                  "object" : "header__settings.show_more_tool_button",
                  "edge" : "top"
                },
                "to" : {
                  "object" : "screen",
                  "edge" : "top"
                },
                "expectedDistance" : "55px",
                "realDistance" : "55px"
              } ],
              "highlight" : [ "header__settings.show_more_tool_button", "screen" ]
            }, {
              "status" : "info",
              "place" : {
                "filePath" : "specs/post/postPage.gspec",
                "lineNumber" : 97
              },
              "name" : "right-of toolbar",
              "meta" : [ {
                "from" : {
                  "object" : "header__settings.show_more_tool_button",
                  "edge" : "left"
                },
                "to" : {
                  "object" : "toolbar",
                  "edge" : "right"
                },
                "expectedDistance" : ">= 0px",
                "realDistance" : "416px"
              } ],
              "highlight" : [ "header__settings.show_more_tool_button", "toolbar" ]
            }, {
              "status" : "info",
              "place" : {
                "filePath" : "specs/post/postPage.gspec",
                "lineNumber" : 98
              },
              "name" : "width 24px",
              "meta" : [ {
                "from" : {
                  "object" : "header__settings.show_more_tool_button",
                  "edge" : "left"
                },
                "to" : {
                  "object" : "header__settings.show_more_tool_button",
                  "edge" : "right"
                },
                "expectedDistance" : "24px",
                "realDistance" : "24px"
              } ],
              "highlight" : [ "header__settings.show_more_tool_button" ]
            } ]
          } ],
          "sections" : [ {
            "name" : "editor_body.title_textfield, editor_body.content_textfield are aligned vertically above each other with 9px margin",
            "place" : {
              "filePath" : "specs/post/postPage.gspec",
              "lineNumber" : 67
            },
            "objects" : [ {
              "name" : "editor_body.title_textfield",
              "specs" : [ {
                "status" : "info",
                "place" : {
                  "filePath" : "specs\\post/../galen-extras/galen-extras-rules.gspec",
                  "lineNumber" : 197
                },
                "name" : "aligned vertically all editor_body.content_textfield",
                "highlight" : [ "editor_body.title_textfield", "editor_body.content_textfield" ]
              }, {
                "status" : "info",
                "place" : {
                  "filePath" : "specs\\post/../galen-extras/galen-extras-rules.gspec",
                  "lineNumber" : 198
                },
                "name" : "above editor_body.content_textfield 9px",
                "meta" : [ {
                  "from" : {
                    "object" : "editor_body.title_textfield",
                    "edge" : "bottom"
                  },
                  "to" : {
                    "object" : "editor_body.content_textfield",
                    "edge" : "top"
                  },
                  "expectedDistance" : "9px",
                  "realDistance" : "9px"
                } ],
                "highlight" : [ "editor_body.title_textfield", "editor_body.content_textfield" ]
              } ]
            } ]
          } ]
        }, {
          "name" : "Toolbar elements",
          "place" : {
            "filePath" : "specs/post/postPage.gspec",
            "lineNumber" : 100
          },
          "objects" : [ {
            "name" : "toolbar.insert_button",
            "specs" : [ {
              "status" : "info",
              "place" : {
                "filePath" : "specs/post/postPage.gspec",
                "lineNumber" : 118
              },
              "name" : "centered horizontally inside toolbar 1px",
              "highlight" : [ "toolbar.insert_button", "toolbar" ]
            }, {
              "status" : "info",
              "place" : {
                "filePath" : "specs/post/postPage.gspec",
                "lineNumber" : 119
              },
              "name" : "inside toolbar 6px bottom, 5px top, 0px left right",
              "meta" : [ {
                "from" : {
                  "object" : "toolbar.insert_button",
                  "edge" : "bottom"
                },
                "to" : {
                  "object" : "toolbar",
                  "edge" : "bottom"
                },
                "expectedDistance" : "6px",
                "realDistance" : "6px"
              }, {
                "from" : {
                  "object" : "toolbar.insert_button",
                  "edge" : "top"
                },
                "to" : {
                  "object" : "toolbar",
                  "edge" : "top"
                },
                "expectedDistance" : "5px",
                "realDistance" : "5px"
              }, {
                "from" : {
                  "object" : "toolbar.insert_button",
                  "edge" : "left"
                },
                "to" : {
                  "object" : "toolbar",
                  "edge" : "left"
                },
                "expectedDistance" : "0px",
                "realDistance" : "0px"
              }, {
                "from" : {
                  "object" : "toolbar.insert_button",
                  "edge" : "right"
                },
                "to" : {
                  "object" : "toolbar",
                  "edge" : "right"
                },
                "expectedDistance" : "0px",
                "realDistance" : "0px"
              } ],
              "highlight" : [ "toolbar.insert_button", "toolbar" ]
            } ]
          } ]
        }, {
          "name" : "Header__settings elements",
          "place" : {
            "filePath" : "specs/post/postPage.gspec",
            "lineNumber" : 121
          },
          "objects" : [ {
            "name" : "header__settings.preview_button",
            "specs" : [ {
              "status" : "info",
              "place" : {
                "filePath" : "specs/post/postPage.gspec",
                "lineNumber" : 147
              },
              "name" : "inside header__settings 7px top bottom, 2px left",
              "meta" : [ {
                "from" : {
                  "object" : "header__settings.preview_button",
                  "edge" : "top"
                },
                "to" : {
                  "object" : "header__settings",
                  "edge" : "top"
                },
                "expectedDistance" : "7px",
                "realDistance" : "7px"
              }, {
                "from" : {
                  "object" : "header__settings.preview_button",
                  "edge" : "bottom"
                },
                "to" : {
                  "object" : "header__settings",
                  "edge" : "bottom"
                },
                "expectedDistance" : "7px",
                "realDistance" : "7px"
              }, {
                "from" : {
                  "object" : "header__settings.preview_button",
                  "edge" : "left"
                },
                "to" : {
                  "object" : "header__settings",
                  "edge" : "left"
                },
                "expectedDistance" : "2px",
                "realDistance" : "2px"
              } ],
              "highlight" : [ "header__settings.preview_button", "header__settings" ]
            }, {
              "status" : "info",
              "place" : {
                "filePath" : "specs/post/postPage.gspec",
                "lineNumber" : 148
              },
              "name" : "width 56px",
              "meta" : [ {
                "from" : {
                  "object" : "header__settings.preview_button",
                  "edge" : "left"
                },
                "to" : {
                  "object" : "header__settings.preview_button",
                  "edge" : "right"
                },
                "expectedDistance" : "56px",
                "realDistance" : "56px"
              } ],
              "highlight" : [ "header__settings.preview_button" ]
            }, {
              "status" : "info",
              "place" : {
                "filePath" : "specs/post/postPage.gspec",
                "lineNumber" : 163
              },
              "name" : "height 33px",
              "meta" : [ {
                "from" : {
                  "object" : "header__settings.preview_button",
                  "edge" : "top"
                },
                "to" : {
                  "object" : "header__settings.preview_button",
                  "edge" : "bottom"
                },
                "expectedDistance" : "33px",
                "realDistance" : "33px"
              } ],
              "highlight" : [ "header__settings.preview_button" ]
            } ]
          }, {
            "name" : "header__settings.setting_button.icon_setting",
            "specs" : [ {
              "status" : "info",
              "place" : {
                "filePath" : "specs/post/postPage.gspec",
                "lineNumber" : 151
              },
              "name" : "centered horizontally inside header__settings.setting_button 1px",
              "highlight" : [ "header__settings.setting_button.icon_setting", "header__settings.setting_button" ]
            }, {
              "status" : "info",
              "place" : {
                "filePath" : "specs/post/postPage.gspec",
                "lineNumber" : 152
              },
              "name" : "inside header__settings.setting_button 8px top left right bottom",
              "meta" : [ {
                "from" : {
                  "object" : "header__settings.setting_button.icon_setting",
                  "edge" : "top"
                },
                "to" : {
                  "object" : "header__settings.setting_button",
                  "edge" : "top"
                },
                "expectedDistance" : "8px",
                "realDistance" : "8px"
              }, {
                "from" : {
                  "object" : "header__settings.setting_button.icon_setting",
                  "edge" : "left"
                },
                "to" : {
                  "object" : "header__settings.setting_button",
                  "edge" : "left"
                },
                "expectedDistance" : "8px",
                "realDistance" : "8px"
              }, {
                "from" : {
                  "object" : "header__settings.setting_button.icon_setting",
                  "edge" : "right"
                },
                "to" : {
                  "object" : "header__settings.setting_button",
                  "edge" : "right"
                },
                "expectedDistance" : "8px",
                "realDistance" : "8px"
              }, {
                "from" : {
                  "object" : "header__settings.setting_button.icon_setting",
                  "edge" : "bottom"
                },
                "to" : {
                  "object" : "header__settings.setting_button",
                  "edge" : "bottom"
                },
                "expectedDistance" : "8px",
                "realDistance" : "8px"
              } ],
              "highlight" : [ "header__settings.setting_button.icon_setting", "header__settings.setting_button" ]
            } ]
          }, {
            "name" : "header__settings.publish_button",
            "specs" : [ {
              "status" : "info",
              "place" : {
                "filePath" : "specs/post/postPage.gspec",
                "lineNumber" : 155
              },
              "name" : "inside header__settings 7px top bottom",
              "meta" : [ {
                "from" : {
                  "object" : "header__settings.publish_button",
                  "edge" : "top"
                },
                "to" : {
                  "object" : "header__settings",
                  "edge" : "top"
                },
                "expectedDistance" : "7px",
                "realDistance" : "7px"
              }, {
                "from" : {
                  "object" : "header__settings.publish_button",
                  "edge" : "bottom"
                },
                "to" : {
                  "object" : "header__settings",
                  "edge" : "bottom"
                },
                "expectedDistance" : "7px",
                "realDistance" : "7px"
              } ],
              "highlight" : [ "header__settings.publish_button", "header__settings" ]
            }, {
              "status" : "info",
              "place" : {
                "filePath" : "specs/post/postPage.gspec",
                "lineNumber" : 156
              },
              "name" : "left-of header__settings.setting_button 2px",
              "meta" : [ {
                "from" : {
                  "object" : "header__settings.publish_button",
                  "edge" : "right"
                },
                "to" : {
                  "object" : "header__settings.setting_button",
                  "edge" : "left"
                },
                "expectedDistance" : "2px",
                "realDistance" : "2px"
              } ],
              "highlight" : [ "header__settings.publish_button", "header__settings.setting_button" ]
            }, {
              "status" : "info",
              "place" : {
                "filePath" : "specs/post/postPage.gspec",
                "lineNumber" : 157
              },
              "name" : "width 63px",
              "meta" : [ {
                "from" : {
                  "object" : "header__settings.publish_button",
                  "edge" : "left"
                },
                "to" : {
                  "object" : "header__settings.publish_button",
                  "edge" : "right"
                },
                "expectedDistance" : "63px",
                "realDistance" : "63px"
              } ],
              "highlight" : [ "header__settings.publish_button" ]
            }, {
              "status" : "info",
              "place" : {
                "filePath" : "specs/post/postPage.gspec",
                "lineNumber" : 163
              },
              "name" : "height 33px",
              "meta" : [ {
                "from" : {
                  "object" : "header__settings.publish_button",
                  "edge" : "top"
                },
                "to" : {
                  "object" : "header__settings.publish_button",
                  "edge" : "bottom"
                },
                "expectedDistance" : "33px",
                "realDistance" : "33px"
              } ],
              "highlight" : [ "header__settings.publish_button" ]
            } ]
          }, {
            "name" : "header__settings.setting_button",
            "specs" : [ {
              "status" : "info",
              "place" : {
                "filePath" : "specs/post/postPage.gspec",
                "lineNumber" : 160
              },
              "name" : "inside header__settings 6px bottom, 5px top, 19px right",
              "meta" : [ {
                "from" : {
                  "object" : "header__settings.setting_button",
                  "edge" : "bottom"
                },
                "to" : {
                  "object" : "header__settings",
                  "edge" : "bottom"
                },
                "expectedDistance" : "6px",
                "realDistance" : "6px"
              }, {
                "from" : {
                  "object" : "header__settings.setting_button",
                  "edge" : "top"
                },
                "to" : {
                  "object" : "header__settings",
                  "edge" : "top"
                },
                "expectedDistance" : "5px",
                "realDistance" : "5px"
              }, {
                "from" : {
                  "object" : "header__settings.setting_button",
                  "edge" : "right"
                },
                "to" : {
                  "object" : "header__settings",
                  "edge" : "right"
                },
                "expectedDistance" : "19px",
                "realDistance" : "19px"
              } ],
              "highlight" : [ "header__settings.setting_button", "header__settings" ]
            } ]
          } ],
          "sections" : [ {
            "name" : "header__settings.preview_button, header__settings.publish_button are aligned horizontally next to each other with 5px margin",
            "place" : {
              "filePath" : "specs/post/postPage.gspec",
              "lineNumber" : 144
            },
            "objects" : [ {
              "name" : "header__settings.preview_button",
              "specs" : [ {
                "status" : "info",
                "place" : {
                  "filePath" : "specs\\post/../galen-extras/galen-extras-rules.gspec",
                  "lineNumber" : 184
                },
                "name" : "aligned horizontally all header__settings.publish_button",
                "highlight" : [ "header__settings.preview_button", "header__settings.publish_button" ]
              }, {
                "status" : "info",
                "place" : {
                  "filePath" : "specs\\post/../galen-extras/galen-extras-rules.gspec",
                  "lineNumber" : 185
                },
                "name" : "left-of header__settings.publish_button 5px",
                "meta" : [ {
                  "from" : {
                    "object" : "header__settings.preview_button",
                    "edge" : "right"
                  },
                  "to" : {
                    "object" : "header__settings.publish_button",
                    "edge" : "left"
                  },
                  "expectedDistance" : "5px",
                  "realDistance" : "5px"
                } ],
                "highlight" : [ "header__settings.preview_button", "header__settings.publish_button" ]
              } ]
            } ]
          } ]
        } ],
        "objects" : {
          "editor_body.content_label" : {
            "area" : [ 15, 190, 1, 1 ]
          },
          "screen" : {
            "area" : [ 0, 0, 480, 885 ]
          },
          "header__settings.preview_button" : {
            "area" : [ 296, 57, 56, 33 ]
          },
          "header__settings.setting_button.icon_setting" : {
            "area" : [ 430, 63, 20, 20 ]
          },
          "header__settings.setting_button" : {
            "area" : [ 422, 55, 36, 36 ]
          },
          "editor_body.title_textfield" : {
            "area" : [ 16, 191, 480, 84 ]
          },
          "toolbar" : {
            "area" : [ 2, 50, 36, 47 ]
          },
          "header__settings" : {
            "area" : [ 294, 50, 183, 47 ]
          },
          "toolbar.insert_button" : {
            "area" : [ 2, 55, 36, 36 ]
          },
          "editor_body.content_textfield" : {
            "area" : [ 16, 284, 480, 200 ]
          },
          "editor_body" : {
            "area" : [ 16, 146, 480, 338 ]
          },
          "header__settings.publish_button" : {
            "area" : [ 357, 57, 63, 33 ]
          },
          "header__settings.show_more_tool_button" : {
            "area" : [ 454, 55, 24, 36 ]
          }
        },
        "screenshot" : "layout-1-screenshot.png",
        "type" : "layout"
      } ],
      "time" : 1558599765906,
      "type" : "node"
    } ]
  }
}